LICENSE
README.md
setup.py
tpm.py
tpm.egg-info/PKG-INFO
tpm.egg-info/SOURCES.txt
tpm.egg-info/dependency_links.txt
tpm.egg-info/requires.txt
tpm.egg-info/top_level.txt