Metadata-Version: 2.1
Name: tpm
Version: 4.2
Summary: Provides functions to work with TeamPasswordManager API.
Home-page: https://github.com/peshay/tpm
Author: Andreas Hubert
Author-email: anhubert@gmail.com
License: MIT
Keywords: TeamPasswordManager json api
Platform: UNKNOWN
Classifier: Development Status :: 5 - Production/Stable
Classifier: Intended Audience :: Developers
Classifier: Topic :: Software Development :: Libraries :: Application Frameworks
Classifier: License :: OSI Approved :: MIT License
Classifier: Programming Language :: Python :: 3.6
Classifier: Programming Language :: Python :: 3.7
Classifier: Programming Language :: Python :: 3.8
Classifier: Programming Language :: Python :: 3.9
License-File: LICENSE
